mfd_host/__init__.py
mfd_host/base.py
mfd_host/esxi.py
mfd_host/exceptions.py
mfd_host/freebsd.py
mfd_host/linux.py
mfd_host/windows.py
mfd_host/feature/__init__.py
mfd_host/feature/base/__init__.py
mfd_host/feature/base/base.py
mfd_host/feature/cpu/__init__.py
mfd_host/feature/cpu/base.py
mfd_host/feature/cpu/const.py
mfd_host/feature/cpu/esxi.py
mfd_host/feature/cpu/freebsd.py
mfd_host/feature/cpu/linux.py
mfd_host/feature/cpu/windows.py
mfd_host/feature/device/__init__.py
mfd_host/feature/device/base.py
mfd_host/feature/device/device_const.py
mfd_host/feature/device/windows.py
mfd_host/feature/memory/__init__.py
mfd_host/feature/memory/base.py
mfd_host/feature/memory/esxi.py
mfd_host/feature/memory/exceptions.py
mfd_host/feature/memory/freebsd.py
mfd_host/feature/memory/linux.py
mfd_host/feature/memory/windows.py
mfd_host/feature/service/__init__.py
mfd_host/feature/service/base.py
mfd_host/feature/service/esxi.py
mfd_host/feature/service/freebsd.py
mfd_host/feature/service/linux.py
mfd_host/feature/service/windows.py
mfd_host/feature/stats/__init__.py
mfd_host/feature/stats/base.py
mfd_host/feature/stats/data_structures.py
mfd_host/feature/stats/esxi.py
mfd_host/feature/stats/freebsd.py
mfd_host/feature/stats/linux.py
mfd_host/feature/stats/windows.py
mfd_host/feature/utils/__init__.py
mfd_host/feature/utils/base.py
mfd_host/feature/utils/esxi.py
mfd_host/feature/utils/freebsd.py
mfd_host/feature/utils/linux.py
mfd_host/feature/utils/windows.py
mfd_host-2.1.0.dist-info/licenses/AUTHORS.md
mfd_host-2.1.0.dist-info/licenses/LICENSE.md
mfd_host-2.1.0.dist-info/METADATA
mfd_host-2.1.0.dist-info/WHEEL
mfd_host-2.1.0.dist-info/top_level.txt
mfd_host-2.1.0.dist-info/RECORD
