Metadata-Version: 2.4
Name: mfd-host
Version: 2.1.0
Summary: MFD Host provides a unified Python interface for managing and interacting with Systems Under Tests (SUTs) AKA Hosts and their capabilities across multiple operating systems.
Project-URL: Homepage, https://github.com/intel/mfd
Project-URL: Repository, https://github.com/intel/mfd-host
Project-URL: Issues, https://github.com/intel/mfd-host/issues
Project-URL: Changelog, https://github.com/intel/mfd-host/blob/main/CHANGELOG.md
Requires-Python: <3.14,>=3.10
License-File: LICENSE.md
License-File: AUTHORS.md
Requires-Dist: mfd-connect>=7.12.0
Requires-Dist: mfd-common-libs>=1.11.0
Requires-Dist: mfd-devcon>=2.0.0
Requires-Dist: mfd-typing>=1.23.0
Requires-Dist: mfd-package-manager<4,>=3
Requires-Dist: mfd-network-adapter<15,>=14
Requires-Dist: mfd-kvm<4,>=3.12.0
Requires-Dist: mfd-hyperv<3,>=2.1.0
Requires-Dist: mfd-esxi<4,>=3.2.0
Requires-Dist: mfd-model[config]>=0.9.0
Requires-Dist: mfd-mount>=1.8.0
Requires-Dist: mfd-base-tool>=2.7.0
Requires-Dist: mfd-sysctl<2,>=1.6.0
Requires-Dist: mfd-dmesg<2,>=1.20.0
Requires-Dist: mfd_event_log<1,>=0.9.0
Dynamic: license-file
